{"name":"3d printing","slug":"3d-printing","count":1,"postlist":[{"title":"Agnikul Cosmos","uid":"2b18e0f83375bbbf56710f240ee4e963","slug":"agnikul-cosmos","date":"2021-03-29T09:59:18.000Z","updated":"2024-05-27T10:37:17.904Z","comments":true,"path":"api/articles/agnikul-cosmos.json","keywords":null,"cover":"images/posts/agnikul-cosmos.png","text":"Agnikul “Agnikul” is a derivative of the Sanskrit word - “Gurukul” and it could ...","link":"","photos":[],"count_time":{"symbolsCount":"4k","symbolsTime":"4 mins."},"categories":[{"name":"technology","slug":"technology","count":3,"path":"api/categories/technology.json"}],"tags":[{"name":"technology","slug":"technology","count":14,"path":"api/tags/technology.json"},{"name":"information","slug":"information","count":2,"path":"api/tags/information.json"},{"name":"3d printing","slug":"3d-printing","count":1,"path":"api/tags/3d-printing.json"},{"name":"inventions","slug":"inventions","count":1,"path":"api/tags/inventions.json"}],"author":{"name":"Mr. Blogger","slug":"blog-author","avatar":"https://www.mistrysiddh.com/images/whoami/avatar.png","link":"https://www.mistrysiddh.com/","description":"","socials":{"github":"","twitter":"","stackoverflow":"","wechat":"","qq":"","weibo":"","zhihu":"","csdn":"","juejin":"","customs":{}}}}]}